dash_handsontable/HotTable.py
dash_handsontable/__init__.py
dash_handsontable/_imports_.py
dash_handsontable/dash_handsontable.js
dash_handsontable/metadata.json
dash_handsontable/package-info.json
dash_handsontable-0.1.2.dist-info/LICENSE
dash_handsontable-0.1.2.dist-info/METADATA
dash_handsontable-0.1.2.dist-info/WHEEL
dash_handsontable-0.1.2.dist-info/top_level.txt
dash_handsontable-0.1.2.dist-info/RECORD
