Metadata-Version: 2.1
Name: dash_handsontable
Version: 0.1.2
Summary: Handsontable for Plotly Dash
Home-page: https://github.com/DhiraPT/dash-handsontable
Author: Dhiraputta Pathama Tengara
Author-email: dhira.pt@gmail.com>
License: MIT
Project-URL: Documentation, https://github.com/DhiraPT/dash-handsontable
Project-URL: Download, https://github.com/DhiraPT/dash-handsontable/tags
Project-URL: Issue Tracker, https://github.com/DhiraPT/dash-handsontable/issues
Project-URL: Source, https://github.com/DhiraPT/dash-handsontable
Classifier: Development Status :: 1 - Planning
Classifier: Environment :: Web Environment
Classifier: Framework :: Dash
Classifier: Intended Audience :: Developers
Classifier: License :: OSI Approved :: MIT License
Classifier: Programming Language :: Python
Classifier: Programming Language :: Python :: 3
Classifier: Programming Language :: Python :: 3.8
Classifier: Programming Language :: Python :: 3.9
Classifier: Programming Language :: Python :: 3.10
Classifier: Programming Language :: Python :: 3.11
Classifier: Programming Language :: Python :: 3.12
Classifier: Topic :: Software Development :: User Interfaces
Requires-Python: >=3.8
License-File: LICENSE
Requires-Dist: dash >=2.5.1
